{
  "BaseResp": {
    "StatusCode": 0,
    "StatusMessage": "success"
  },
  "code": 0,
  "data": {
    "common_list_info": {
      "cursor": "",
      "has_more": false,
      "log_extra": {
        "recommend_info": "{\"channel_id\":\"\",\"request_id\":\"2026032017063582D05482000574846663\"}"
      },
      "total": 45
    },
    "data_list": [
      {
        "comment": {
          "comment_id": "7297598274612249371",
          "common": {
            "comment_type": 20,
            "content": {
              "image_data_list": {},
              "text": "角色塑造的很成功，在爽文中又带着慢热文的丰富感，人物较为饱满丰富，算是给又想看爽文求快又不会感到干巴的良文了，在番茄里不多了 ，作者加油（真的很喜欢小挂件）"
            },
            "content_type": 0,
            "create_timestamp": 1699105257,
            "group_id": "7287895438420610063",
            "service_id": 2,
            "status": 1,
            "user_info": {
              "base_info": {
                "description": "书本大户",
                "encode_user_id": "#c1967_MTk2NzE5NjcxOTY3MTk2NxEWKWpY7+3mCzCE56sWEuFtCovqWVVUz9a0CaE1jB2W",
                "gender": 0,
                "is_cancelled": false,
                "profile_gender": 0,
                "user_avatar": "http://p3-reading-sign.fqnovelpic.com/tos-cn-i-1yzifmftcy/8d4191080d454b6b930697bbc246bfb0~tplv-s85hriknmn-jpeg-v1:144:0.jpeg?lk3s=9b9bd2b1&x-expires=1776532514&x-signature=CKL74gpiYHXsgBYUHfXbQWeSDIs%3D",
                "user_id": "2510920311641396",
                "user_name": "不如门神"
              },
              "expand_extra": {},
              "user_id": "2510920311641396",
              "user_relation": {
                "can_follow": true,
                "relation_type": 1
              },
              "user_tag": {
                "fan_rank_num": 0,
                "fan_ranklist_title": "",
                "is_author": false,
                "is_blue_vip": false,
                "is_cp": false,
                "is_official_cert": false,
                "is_vip": true,
                "sticker": {
                  "expire_time": 1775204951,
                  "is_worn": true,
                  "sticker": {
                    "add_context": "",
                    "bg_color": "#FFF3DD",
                    "can_worn": false,
                    "id": 2,
                    "name": "永不书荒",
                    "small_url": "https://p6-novel.byteimg.com/origin/novel-static/2c704b96a929a7a8b3461ddbf49a8d01",
                    "sticker_type": 1,
                    "url": "https://p3-novel.byteimg.com/origin/novel-static/b93ef223f8131d9ee8e8312f642d9681"
                  }
                },
                "user_title_info": [
                  {
                    "en_title": "svip",
                    "icon": "{\"icon_default_url\":\"https://p6-novel.byteimg.com/origin/novel-static/07d37b2c30d271228698f77f4f7f7daf\",\"icon_dark_url\":\"https://p6-novel.byteimg.com/origin/novel-static/d67f15fefbb4470bb54c773eb84e90d8\",\"icon_width\":26,\"icon_height\":16}",
                    "intro": "{\"title_name\":\"svip\",\"title_id\":\"svip\",\"icon_type\":1}",
                    "is_author_title": false,
                    "is_vip_title": true,
                    "zh_title": "svip"
                  }
                ]
              }
            }
          },
          "expand": {
            "book_id": "7287895438420610063",
            "book_info": {
              "abstract": "【比NPC还坏女主+女强+无CP+无限流+双面人+护短】\n\n“你相比于其他人会更享受依赖型的关系，同时伴有一定的分离焦虑症，独处时心理上的压力会引起一定的生理反应，例如呼吸急促焦虑暴躁等。说的更清楚点，你没办法一个人呆太久。”\n　　心理医生坐在对面看着电脑里最新得到的数据，有条不紊的说出自己经过专业水平判断得出来的经验。\n　　“真的吗医生？”\n　　叶牧语气中满是怀疑，“可我都没有感觉啊，你是怎么看出来的？”\n　　心理医生抬起头，扶了下眼镜，看向办公桌对面的沙发，\n　　“我一会再跟你解释，你先松开我们护士，外面还有很多人在等着呢。”\n　　\n　　一个“依赖型”精神病患者，突然被卷入无限流世界中，那能怎么办？\n　　那就每场随机抓一个小可爱带在身边吧。\n　　\n　　无限世界一直有个传言，有位神秘的大佬在暗中招揽下属，试图一统无限流。\n　　叶·神秘大佬·牧：什么下属？统什么流？\n　　【女主越来越疯！浅丢三观！主打双标！】",
              "audio_thumb_uri": "https://p3-novel.byteimg.com/img/novel-pic/p2odd509e44e7acdf18ae4bbfc58e72467e~tplv-tt-cs0:440:440.image",
              "author": "伏与",
              "author_id": "",
              "book_id": "7287895438420610063",
              "book_name": "依赖症患者在无限流靠发病闯关",
              "book_short_name": "",
              "book_type": "0",
              "color_dominate": "#303028",
              "creation_status": "1",
              "genre": "0",
              "genre_type": "0",
              "read_count_text": "潜力好书",
              "reader_schema": {
                "authorize_type": "1",
                "category_schema": "[{\"category_id\":539,\"name\":\"悬疑脑洞\",\"schema\":\"dragon1967://newCategoryDetail?id=539&name=悬疑脑洞&genre_type=0&gender=0&source=detail\"},{\"category_id\":37,\"name\":\"穿越\",\"schema\":\"dragon1967://newCategoryDetail?id=37&name=穿越&genre_type=0&gender=0&source=detail\"},{\"category_id\":10,\"name\":\"悬疑\",\"schema\":\"dragon1967://newCategoryDetail?id=10&name=悬疑&genre_type=0&gender=0&source=detail\"},{\"category_id\":100,\"name\":\"灵异\",\"schema\":\"dragon1967://newCategoryDetail?id=100&name=灵异&genre_type=0&gender=0&source=detail\"},{\"category_id\":86,\"name\":\"女强\",\"schema\":\"dragon1967://newCategoryDetail?id=86&name=女强&genre_type=0&gender=0&source=detail\"},{\"category_id\":70,\"name\":\"无限流\",\"schema\":\"dragon1967://newCategoryDetail?id=70&name=无限流&genre_type=0&gender=0&source=detail\"},{\"category_id\":392,\"name\":\"无CP\",\"schema\":\"dragon1967://newCategoryDetail?id=392&name=无CP&genre_type=0&gender=0&source=detail\"},{\"category_id\":520,\"name\":\"大佬\",\"schema\":\"dragon1967://newCategoryDetail?id=520&name=大佬&genre_type=0&gender=0&source=detail\"}]",
                "first_chapter_item_id": "7287896687853437502",
                "read_count": "694",
                "title_page_tags": "",
                "word_number": "470145"
              },
              "relate_post_id": "",
              "relate_post_schema": "",
              "score": "6.7",
              "serial_count": "208",
              "tags": "悬疑脑洞,穿越,女强,灵异,无CP,大佬,悬疑,无限流",
              "thumb_url": "https://p3-reading-sign.fqnovelpic.com/novel-pic/p2odd509e44e7acdf18ae4bbfc58e72467e~tplv-noop.image?lk3s=9b9bd2b1&x-expires=1779181595&x-signature=mzgDJUHSO%2FrS3dgqrg9szrAR228%3D",
              "tomato_book_status": "1"
            },
            "book_info_list": [],
            "common_stat": {},
            "creator_id": "4152222481122408",
            "extra": {
              "comment_jump_schema": "",
              "novelapp_read_item_cnt": "5.802832e+06"
            },
            "log_extra": {
              "recommend_info": "{\"channel_id\":\"\",\"request_id\":\"2026032017063582D05482000574846663\"}"
            },
            "relate_info_list": [],
            "reply_show_count": 0,
            "reply_show_row": 0,
            "score": "10",
            "score_suffix_text": "阅读2小时后点评"
          },
          "stat": {
            "digg_count": 9,
            "forwarded_count": 0,
            "listen_duration": 0,
            "read_book_count": 0,
            "read_duration": 5802,
            "reply_count": 0,
            "show_pv": 3126
          },
          "user_action": {
            "author": 0,
            "is_author_stick": false,
            "stick_position": 0,
            "user_digg": false,
            "user_disagree": false
          }
        },
        "data_type": 4
      },
      {
        "comment": {
          "comment_id": "7315324522713989899",
          "common": {
            "comment_type": 21,
            "content": {
              "image_data_list": {},
              "text": "好好看，不是第3个副本那个小黄鸭真的好好呀，乖乖的又萌萌的又傻傻的，这种带小挂件就最好了，本来以为这次副本结束就没她是了，没想到他变成了道具，我的天更刺激了\n女主冷静疯批霸道，看完就只能说66666"
            },
            "content_type": 0,
            "create_timestamp": 1703233137,
            "group_id": "7287895438420610063",
            "service_id": 2,
            "status": 1,
            "user_info": {
              "base_info": {
                "description": "没有感情的读书人",
                "encode_user_id": "#c1967_MTk2NzE5NjcxOTY3MTk2N2HoGaRXfH5KeOSI3421OaVM40cYe/vujeWDdeqU207Z",
                "gender": 0,
                "is_cancelled": false,
                "profile_gender": 0,
                "user_avatar": "http://p3-reading-sign.fqnovelpic.com/tos-cn-i-1yzifmftcy/8cacc4f275d4490381a4b9d3b7a774db~tplv-s85hriknmn-jpeg-v1:144:0.jpeg?lk3s=9b9bd2b1&x-expires=1776537223&x-signature=5c9Abk7KDhXvgL1PfDwnZBiOWh0%3D",
                "user_id": "4222537930910414",
                "user_name": "emo雨子"
              },
              "expand_extra": {},
              "user_id": "4222537930910414",
              "user_relation": {
                "can_follow": true,
                "relation_type": 1
              },
              "user_tag": {
                "fan_rank_num": 0,
                "fan_ranklist_title": "",
                "is_author": false,
                "is_blue_vip": false,
                "is_cp": false,
                "is_official_cert": false,
                "is_vip": false,
                "user_title_info": []
              }
            }
          },
          "expand": {
            "book_id": "7287895438420610063",
            "book_info": {
              "abstract": "【比NPC还坏女主+女强+无CP+无限流+双面人+护短】\n\n“你相比于其他人会更享受依赖型的关系，同时伴有一定的分离焦虑症，独处时心理上的压力会引起一定的生理反应，例如呼吸急促焦虑暴躁等。说的更清楚点，你没办法一个人呆太久。”\n　　心理医生坐在对面看着电脑里最新得到的数据，有条不紊的说出自己经过专业水平判断得出来的经验。\n　　“真的吗医生？”\n　　叶牧语气中满是怀疑，“可我都没有感觉啊，你是怎么看出来的？”\n　　心理医生抬起头，扶了下眼镜，看向办公桌对面的沙发，\n　　“我一会再跟你解释，你先松开我们护士，外面还有很多人在等着呢。”\n　　\n　　一个“依赖型”精神病患者，突然被卷入无限流世界中，那能怎么办？\n　　那就每场随机抓一个小可爱带在身边吧。\n　　\n　　无限世界一直有个传言，有位神秘的大佬在暗中招揽下属，试图一统无限流。\n　　叶·神秘大佬·牧：什么下属？统什么流？\n　　【女主越来越疯！浅丢三观！主打双标！】",
              "audio_thumb_uri": "https://p3-novel.byteimg.com/img/novel-pic/p2odd509e44e7acdf18ae4bbfc58e72467e~tplv-tt-cs0:440:440.image",
              "author": "伏与",
              "author_id": "",
              "book_id": "7287895438420610063",
              "book_name": "依赖症患者在无限流靠发病闯关",
              "book_short_name": "",
              "book_type": "0",
              "color_dominate": "#303028",
              "creation_status": "1",
              "genre": "0",
              "genre_type": "0",
              "read_count_text": "潜力好书",
              "reader_schema": {
                "authorize_type": "1",
                "category_schema": "[{\"category_id\":539,\"name\":\"悬疑脑洞\",\"schema\":\"dragon1967://newCategoryDetail?id=539&name=悬疑脑洞&genre_type=0&gender=0&source=detail\"},{\"category_id\":37,\"name\":\"穿越\",\"schema\":\"dragon1967://newCategoryDetail?id=37&name=穿越&genre_type=0&gender=0&source=detail\"},{\"category_id\":10,\"name\":\"悬疑\",\"schema\":\"dragon1967://newCategoryDetail?id=10&name=悬疑&genre_type=0&gender=0&source=detail\"},{\"category_id\":100,\"name\":\"灵异\",\"schema\":\"dragon1967://newCategoryDetail?id=100&name=灵异&genre_type=0&gender=0&source=detail\"},{\"category_id\":86,\"name\":\"女强\",\"schema\":\"dragon1967://newCategoryDetail?id=86&name=女强&genre_type=0&gender=0&source=detail\"},{\"category_id\":70,\"name\":\"无限流\",\"schema\":\"dragon1967://newCategoryDetail?id=70&name=无限流&genre_type=0&gender=0&source=detail\"},{\"category_id\":392,\"name\":\"无CP\",\"schema\":\"dragon1967://newCategoryDetail?id=392&name=无CP&genre_type=0&gender=0&source=detail\"},{\"category_id\":520,\"name\":\"大佬\",\"schema\":\"dragon1967://newCategoryDetail?id=520&name=大佬&genre_type=0&gender=0&source=detail\"}]",
                "first_chapter_item_id": "7287896687853437502",
                "read_count": "694",
                "title_page_tags": "",
                "word_number": "470145"
              },
              "relate_post_id": "",
              "relate_post_schema": "",
              "score": "6.7",
              "serial_count": "208",
              "tags": "悬疑脑洞,穿越,女强,灵异,无CP,大佬,悬疑,无限流",
              "thumb_url": "https://p3-reading-sign.fqnovelpic.com/novel-pic/p2odd509e44e7acdf18ae4bbfc58e72467e~tplv-noop.image?lk3s=9b9bd2b1&x-expires=1779181595&x-signature=mzgDJUHSO%2FrS3dgqrg9szrAR228%3D",
              "tomato_book_status": "1"
            },
            "book_info_list": [],
            "common_stat": {},
            "creator_id": "4152222481122408",
            "extra": {
              "comment_jump_schema": "",
              "novelapp_read_item_cnt": "150"
            },
            "log_extra": {
              "recommend_info": "{\"channel_id\":\"\",\"request_id\":\"2026032017063582D05482000574846663\"}"
            },
            "relate_info_list": [],
            "reply_show_count": 0,
            "reply_show_row": 0,
            "score": "10",
            "score_suffix_text": "阅读6小时后点评"
          },
          "stat": {
            "digg_count": 6,
            "forwarded_count": 0,
            "listen_duration": 0,
            "read_book_count": 0,
            "read_duration": 21861,
            "reply_count": 0,
            "show_pv": 1044
          },
          "user_action": {
            "author": 0,
            "is_author_stick": false,
            "stick_position": 0,
            "user_digg": false,
            "user_disagree": false
          }
        },
        "data_type": 4
      },
      {
        "comment": {
          "comment_id": "7536601216594641688",
          "common": {
            "comment_type": 20,
            "content": {
              "image_data_list": {},
              "text": "好看啊啊啊，别看我只读了这么点时间。其实我在小号已经看完了。真的超级好看，女主很可爱，女主被描写的特别好！！（叠个甲，我在快点看过人面鬼书，比较喜欢无限流的小说，一直找不到代餐，但这个真的很和我的胃口啊！）"
            },
            "content_type": 0,
            "create_timestamp": 1754757377,
            "group_id": "7287895438420610063",
            "service_id": 2,
            "status": 1,
            "user_info": {
              "base_info": {
                "description": "爱吃鱼……爱猫猫……所以我算不算是半只猫猫鱼……？",
                "encode_user_id": "#c1967_MTk2NzE5NjcxOTY3MTk2N+BCa+Fo7W5WZ+ZPxehMNrzz4o7cLmmLuuqP9gWCvqk5",
                "gender": 0,
                "is_cancelled": false,
                "profile_gender": 0,
                "user_avatar": "http://p3-reading-sign.fqnovelpic.com/tos-cn-i-1yzifmftcy/02600ac4832b43b08fc9476a866b2ede~tplv-s85hriknmn-jpeg-v1:144:0.jpeg?lk3s=9b9bd2b1&x-expires=1776529672&x-signature=S%2FPAhsPbY%2BshKl%2BRaXMB3uazjO4%3D",
                "user_id": "1425427375074285",
                "user_name": "小鱼爱吃三文鱼"
              },
              "expand_extra": {},
              "user_id": "1425427375074285",
              "user_relation": {
                "can_follow": true,
                "relation_type": 1
              },
              "user_tag": {
                "fan_rank_num": 0,
                "fan_ranklist_title": "",
                "is_author": false,
                "is_blue_vip": false,
                "is_cp": false,
                "is_official_cert": false,
                "is_vip": false,
                "user_title_info": []
              }
            }
          },
          "expand": {
            "book_id": "7287895438420610063",
            "book_info": {
              "abstract": "【比NPC还坏女主+女强+无CP+无限流+双面人+护短】\n\n“你相比于其他人会更享受依赖型的关系，同时伴有一定的分离焦虑症，独处时心理上的压力会引起一定的生理反应，例如呼吸急促焦虑暴躁等。说的更清楚点，你没办法一个人呆太久。”\n　　心理医生坐在对面看着电脑里最新得到的数据，有条不紊的说出自己经过专业水平判断得出来的经验。\n　　“真的吗医生？”\n　　叶牧语气中满是怀疑，“可我都没有感觉啊，你是怎么看出来的？”\n　　心理医生抬起头，扶了下眼镜，看向办公桌对面的沙发，\n　　“我一会再跟你解释，你先松开我们护士，外面还有很多人在等着呢。”\n　　\n　　一个“依赖型”精神病患者，突然被卷入无限流世界中，那能怎么办？\n　　那就每场随机抓一个小可爱带在身边吧。\n　　\n　　无限世界一直有个传言，有位神秘的大佬在暗中招揽下属，试图一统无限流。\n　　叶·神秘大佬·牧：什么下属？统什么流？\n　　【女主越来越疯！浅丢三观！主打双标！】",
              "audio_thumb_uri": "https://p3-novel.byteimg.com/img/novel-pic/p2odd509e44e7acdf18ae4bbfc58e72467e~tplv-tt-cs0:440:440.image",
              "author": "伏与",
              "author_id": "",
              "book_id": "7287895438420610063",
              "book_name": "依赖症患者在无限流靠发病闯关",
              "book_short_name": "",
              "book_type": "0",
              "color_dominate": "#303028",
              "creation_status": "1",
              "genre": "0",
              "genre_type": "0",
              "read_count_text": "潜力好书",
              "reader_schema": {
                "authorize_type": "1",
                "category_schema": "[{\"category_id\":539,\"name\":\"悬疑脑洞\",\"schema\":\"dragon1967://newCategoryDetail?id=539&name=悬疑脑洞&genre_type=0&gender=0&source=detail\"},{\"category_id\":37,\"name\":\"穿越\",\"schema\":\"dragon1967://newCategoryDetail?id=37&name=穿越&genre_type=0&gender=0&source=detail\"},{\"category_id\":10,\"name\":\"悬疑\",\"schema\":\"dragon1967://newCategoryDetail?id=10&name=悬疑&genre_type=0&gender=0&source=detail\"},{\"category_id\":100,\"name\":\"灵异\",\"schema\":\"dragon1967://newCategoryDetail?id=100&name=灵异&genre_type=0&gender=0&source=detail\"},{\"category_id\":86,\"name\":\"女强\",\"schema\":\"dragon1967://newCategoryDetail?id=86&name=女强&genre_type=0&gender=0&source=detail\"},{\"category_id\":70,\"name\":\"无限流\",\"schema\":\"dragon1967://newCategoryDetail?id=70&name=无限流&genre_type=0&gender=0&source=detail\"},{\"category_id\":392,\"name\":\"无CP\",\"schema\":\"dragon1967://newCategoryDetail?id=392&name=无CP&genre_type=0&gender=0&source=detail\"},{\"category_id\":520,\"name\":\"大佬\",\"schema\":\"dragon1967://newCategoryDetail?id=520&name=大佬&genre_type=0&gender=0&source=detail\"}]",
                "first_chapter_item_id": "7287896687853437502",
                "read_count": "694",
                "title_page_tags": "",
                "word_number": "470145"
              },
              "relate_post_id": "",
              "relate_post_schema": "",
              "score": "6.7",
              "serial_count": "208",
              "tags": "悬疑脑洞,穿越,女强,灵异,无CP,大佬,悬疑,无限流",
              "thumb_url": "https://p3-reading-sign.fqnovelpic.com/novel-pic/p2odd509e44e7acdf18ae4bbfc58e72467e~tplv-noop.image?lk3s=9b9bd2b1&x-expires=1779181595&x-signature=mzgDJUHSO%2FrS3dgqrg9szrAR228%3D",
              "tomato_book_status": "1"
            },
            "book_info_list": [],
            "common_stat": {},
            "creator_id": "4152222481122408",
            "extra": {
              "comment_jump_schema": "",
              "novelapp_read_item_cnt": "4"
            },
            "log_extra": {
              "recommend_info": "{\"channel_id\":\"\",\"request_id\":\"2026032017063582D05482000574846663\"}"
            },
            "relate_info_list": [],
            "reply_show_count": 0,
            "reply_show_row": 0,
            "score": "10",
            "score_suffix_text": "阅读不足30分钟后点评"
          },
          "stat": {
            "digg_count": 3,
            "forwarded_count": 0,
            "listen_duration": 0,
            "read_book_count": 0,
            "read_duration": 1799,
            "reply_count": 1,
            "show_pv": 141
          },
          "user_action": {
            "author": 0,
            "is_author_stick": false,
            "stick_position": 0,
            "user_digg": false,
            "user_disagree": false
          }
        },
        "data_type": 4
      }
    ],
    "extra": {
      "book_info": {
        "abstract": "",
        "audio_thumb_uri": "",
        "author": "",
        "author_id": "",
        "book_id": "7287895438420610063",
        "book_name": "",
        "book_type": "",
        "color_dominate": "",
        "creation_status": "",
        "genre": "",
        "genre_type": "",
        "score": "",
        "serial_count": "",
        "tags": "",
        "thumb_url": "",
        "tomato_book_status": ""
      },
      "filter_tag": [],
      "hot_word_search": [],
      "score_cnt": 112,
      "score_text": "112人点评"
    }
  },
  "debug_info": "",
  "log_id": "2026032017063582D05482000574846663",
  "message": "请求成功"
}