{
  "BaseResp": {
    "StatusCode": 0,
    "StatusMessage": "success"
  },
  "code": 0,
  "data": {
    "common_list_info": {
      "cursor": "",
      "has_more": false,
      "log_extra": {
        "recommend_info": "{\"channel_id\":\"\",\"request_id\":\"20260321180519098A676446F773843AC5\"}"
      },
      "total": 2185
    },
    "data_list": [
      {
        "comment": {
          "comment_id": "7273023319023682362",
          "common": {
            "comment_type": 0,
            "content": {
              "image_data_list": {},
              "text": "个性鲜明活灵活现，完全甩其他书主角几条街"
            },
            "content_type": 0,
            "create_timestamp": 1693382825,
            "group_id": "7165309701129767968",
            "service_id": 2,
            "status": 1,
            "user_info": {
              "base_info": {
                "description": "",
                "encode_user_id": "#c1967_MTk2NzE5NjcxOTY3MTk2Nyf1tC+9k/Eh8B2jAqvBRAs=",
                "gender": 1,
                "is_cancelled": false,
                "profile_gender": 1,
                "user_avatar": "http://p3-reading-sign.fqnovelpic.com/tos-cn-i-1yzifmftcy/6c64710e97a743dbb2871f00503797c7~tplv-s85hriknmn-jpeg-v1:144:0.jpeg?lk3s=9b9bd2b1&x-expires=1776621249&x-signature=BjUFX9i%2Fo61Z0QSDFZmK%2FypYg7o%3D",
                "user_id": "831701374471072",
                "user_name": "只做素股"
              },
              "expand_extra": {},
              "user_id": "831701374471072",
              "user_relation": {
                "can_follow": true,
                "relation_type": 1
              },
              "user_tag": {
                "fan_rank_num": 0,
                "fan_ranklist_title": "",
                "is_author": false,
                "is_blue_vip": false,
                "is_cp": false,
                "is_official_cert": false,
                "is_vip": false,
                "user_title_info": []
              }
            }
          },
          "expand": {
            "book_id": "7165309701129767968",
            "book_info": {
              "abstract": "孤儿李星月穿越南宋，本打算拜入全真教，结果被拒。\n成为全真内照顾菜园子的小童儿，心有不甘的他盗了王重阳的墓，得到九阴真经。\n又去少林寻得九阳神功，在小菜园内勤学苦练。\n神功有成后，下山闯荡江湖，成为和赤练仙子齐名的无情仙君。\n并称江湖两大祸害。",
              "audio_thumb_uri": "https://p3-novel.byteimg.com/origin/novel-static/8ae763e02e282c82a0735025ccbc0de9",
              "author": "小米虫",
              "author_id": "",
              "book_id": "7165309701129767968",
              "book_name": "穿越神雕之江湖祸害",
              "book_short_name": "神雕小无赖",
              "book_type": "0",
              "color_dominate": "#e0c8d0",
              "creation_status": "1",
              "genre": "0",
              "genre_type": "0",
              "read_count_text": "7.9万人在读",
              "reader_schema": {
                "authorize_type": "1",
                "category_schema": "[{\"category_id\":1016,\"name\":\"男频衍生\",\"schema\":\"dragon1967://newCategoryDetail?id=1016&name=男频衍生&genre_type=0&gender=1&source=detail\"},{\"category_id\":37,\"name\":\"穿越\",\"schema\":\"dragon1967://newCategoryDetail?id=37&name=穿越&genre_type=0&gender=1&source=detail\"},{\"category_id\":16,\"name\":\"武侠\",\"schema\":\"dragon1967://newCategoryDetail?id=16&name=武侠&genre_type=0&gender=1&source=detail\"},{\"category_id\":384,\"name\":\"无敌\",\"schema\":\"dragon1967://newCategoryDetail?id=384&name=无敌&genre_type=0&gender=1&source=detail\"},{\"category_id\":522,\"name\":\"打脸\",\"schema\":\"dragon1967://newCategoryDetail?id=522&name=打脸&genre_type=0&gender=1&source=detail\"},{\"category_id\":538,\"name\":\"同人\",\"schema\":\"dragon1967://newCategoryDetail?id=538&name=同人&genre_type=0&gender=1&source=detail\"},{\"category_id\":1079,\"name\":\"衍生\",\"schema\":\"dragon1967://newCategoryDetail?id=1079&name=衍生&genre_type=0&gender=1&source=detail\"}]",
                "first_chapter_item_id": "7165314974024532517",
                "read_count": "78219",
                "title_page_tags": "",
                "word_number": "975670"
              },
              "relate_post_id": "",
              "relate_post_schema": "",
              "score": "7.5",
              "serial_count": "366",
              "tags": "男频衍生,武侠,穿越,无敌,打脸,同人,衍生",
              "thumb_url": "https://p3-reading-sign.fqnovelpic.com/novel-pic/77f19d5bced9088f8aecb98b31519b8b~tplv-noop.image?lk3s=9b9bd2b1&x-expires=1779271519&x-signature=xlW9H3PKxpPWz4n4Z0S83%2BH04p0%3D",
              "tomato_book_status": "1"
            },
            "book_info_list": [],
            "common_stat": {},
            "creator_id": "63700036741",
            "extra": {
              "comment_jump_schema": "",
              "novelapp_read_item_cnt": "1.3574183e+07"
            },
            "log_extra": {
              "recommend_info": "{\"channel_id\":\"\",\"request_id\":\"20260321180519098A676446F773843AC5\"}"
            },
            "relate_info_list": [],
            "reply_show_count": 0,
            "reply_show_row": 0,
            "score": "10",
            "score_suffix_text": "阅读6小时后点评"
          },
          "stat": {
            "digg_count": 4,
            "forwarded_count": 0,
            "listen_duration": 7641,
            "read_book_count": 0,
            "read_duration": 21215,
            "reply_count": 0,
            "show_pv": 4810
          },
          "user_action": {
            "author": 0,
            "is_author_stick": false,
            "stick_position": 0,
            "user_digg": false,
            "user_disagree": false
          }
        },
        "data_type": 4
      },
      {
        "comment": {
          "comment_id": "7263126925098582799",
          "common": {
            "comment_type": 20,
            "content": {
              "image_data_list": {},
              "text": "讲句良心话，我感觉这本书真的写的不错，脱离了正常人的道德观和价值观，就光这一点，普通人写不了，因为大部分作者写出都会以自己的原型模板代入主角，而这本书就给了我另外一种感受。是真正值得推荐的一本书，虽然评分不高，但是书确实是好书。",
              "text_exts": [
                {
                  "e": 43,
                  "s": 40,
                  "text": "普通人",
                  "tp": 4,
                  "uri": "dragon1967://search?source=44&hyperlink_type=quote_book&directQueryWord=%E6%99%AE%E9%80%9A%E4%BA%BA&directSearchSourceId=cmt_link%23177408751973843AC5%230%23%23&directTabType=0&reportDict=%7B%22comment_id%22%3A%227263126925098582799%22%2C%22enter_from_book_id%22%3A%227165309701129767968%22%2C%22hyperlink_position%22%3A%22book_cover_comment_list_page%22%2C%22hyperlink_type%22%3A%22quote_book%22%2C%22link_name%22%3A%22%E6%99%AE%E9%80%9A%E4%BA%BA%22%2C%22search_sec_entrance%22%3A%22book_cover_comment_list_page%22%7D&halfscreen=false"
                }
              ]
            },
            "content_type": 0,
            "create_timestamp": 1691078638,
            "group_id": "7165309701129767968",
            "service_id": 2,
            "status": 1,
            "user_info": {
              "base_info": {
                "description": "",
                "encode_user_id": "#c1967_MTk2NzE5NjcxOTY3MTk2N+Z2bTaPxHcJzSQGZgweWoceTeWnuAK4zRQAb2x0qt4/",
                "gender": 1,
                "is_cancelled": false,
                "profile_gender": 0,
                "user_avatar": "http://p3-reading-sign.fqnovelpic.com/tos-cn-i-0000/1437c63bc45b464bb1cc6cd6a7b0d4f1~tplv-s85hriknmn-jpeg-v1:144:0.jpeg?lk3s=9b9bd2b1&x-expires=1776614448&x-signature=77B3F2V9HxLK4vsnQuBSstH5PAo%3D",
                "user_id": "1754431553287911",
                "user_name": "爱吃素馅烧麦的惊咦"
              },
              "expand_extra": {},
              "user_id": "1754431553287911",
              "user_relation": {
                "can_follow": true,
                "relation_type": 1
              },
              "user_tag": {
                "fan_rank_num": 0,
                "fan_ranklist_title": "",
                "is_author": false,
                "is_blue_vip": false,
                "is_cp": false,
                "is_official_cert": false,
                "is_vip": false,
                "user_title_info": []
              }
            }
          },
          "expand": {
            "book_id": "7165309701129767968",
            "book_info": {
              "abstract": "孤儿李星月穿越南宋，本打算拜入全真教，结果被拒。\n成为全真内照顾菜园子的小童儿，心有不甘的他盗了王重阳的墓，得到九阴真经。\n又去少林寻得九阳神功，在小菜园内勤学苦练。\n神功有成后，下山闯荡江湖，成为和赤练仙子齐名的无情仙君。\n并称江湖两大祸害。",
              "audio_thumb_uri": "https://p3-novel.byteimg.com/origin/novel-static/8ae763e02e282c82a0735025ccbc0de9",
              "author": "小米虫",
              "author_id": "",
              "book_id": "7165309701129767968",
              "book_name": "穿越神雕之江湖祸害",
              "book_short_name": "神雕小无赖",
              "book_type": "0",
              "color_dominate": "#e0c8d0",
              "creation_status": "1",
              "genre": "0",
              "genre_type": "0",
              "read_count_text": "7.9万人在读",
              "reader_schema": {
                "authorize_type": "1",
                "category_schema": "[{\"category_id\":1016,\"name\":\"男频衍生\",\"schema\":\"dragon1967://newCategoryDetail?id=1016&name=男频衍生&genre_type=0&gender=1&source=detail\"},{\"category_id\":37,\"name\":\"穿越\",\"schema\":\"dragon1967://newCategoryDetail?id=37&name=穿越&genre_type=0&gender=1&source=detail\"},{\"category_id\":16,\"name\":\"武侠\",\"schema\":\"dragon1967://newCategoryDetail?id=16&name=武侠&genre_type=0&gender=1&source=detail\"},{\"category_id\":384,\"name\":\"无敌\",\"schema\":\"dragon1967://newCategoryDetail?id=384&name=无敌&genre_type=0&gender=1&source=detail\"},{\"category_id\":522,\"name\":\"打脸\",\"schema\":\"dragon1967://newCategoryDetail?id=522&name=打脸&genre_type=0&gender=1&source=detail\"},{\"category_id\":538,\"name\":\"同人\",\"schema\":\"dragon1967://newCategoryDetail?id=538&name=同人&genre_type=0&gender=1&source=detail\"},{\"category_id\":1079,\"name\":\"衍生\",\"schema\":\"dragon1967://newCategoryDetail?id=1079&name=衍生&genre_type=0&gender=1&source=detail\"}]",
                "first_chapter_item_id": "7165314974024532517",
                "read_count": "78219",
                "title_page_tags": "",
                "word_number": "975670"
              },
              "relate_post_id": "",
              "relate_post_schema": "",
              "score": "7.5",
              "serial_count": "366",
              "tags": "男频衍生,武侠,穿越,无敌,打脸,同人,衍生",
              "thumb_url": "https://p3-reading-sign.fqnovelpic.com/novel-pic/77f19d5bced9088f8aecb98b31519b8b~tplv-noop.image?lk3s=9b9bd2b1&x-expires=1779271519&x-signature=xlW9H3PKxpPWz4n4Z0S83%2BH04p0%3D",
              "tomato_book_status": "1"
            },
            "book_info_list": [],
            "common_stat": {},
            "creator_id": "63700036741",
            "extra": {
              "comment_jump_schema": "",
              "novelapp_read_item_cnt": "2.9189693e+07"
            },
            "log_extra": {
              "recommend_info": "{\"channel_id\":\"\",\"request_id\":\"20260321180519098A676446F773843AC5\"}"
            },
            "relate_info_list": [],
            "reply_show_count": 0,
            "reply_show_row": 0,
            "score": "10",
            "score_suffix_text": "阅读25小时后点评"
          },
          "stat": {
            "digg_count": 47,
            "forwarded_count": 0,
            "listen_duration": 62198,
            "read_book_count": 0,
            "read_duration": 91387,
            "reply_count": 16,
            "show_pv": 51478
          },
          "user_action": {
            "author": 0,
            "is_author_stick": false,
            "stick_position": 0,
            "user_digg": false,
            "user_disagree": false
          }
        },
        "data_type": 4
      },
      {
        "comment": {
          "comment_id": "7607152860498576152",
          "common": {
            "comment_type": 0,
            "content": {
              "image_data_list": {},
              "text": "这本书还是挺好看的 虽然也有毒点， 但优点也很明显就是节奏很快，毒点一两章就跳到了爽点，不会像别的小说那样恶心你几十章。总的来说挺好"
            },
            "content_type": 0,
            "create_timestamp": 1771186392,
            "group_id": "7165309701129767968",
            "service_id": 2,
            "status": 1,
            "user_info": {
              "base_info": {
                "description": "",
                "encode_user_id": "#c1967_MTk2NzE5NjcxOTY3MTk2N09P5HJAZCJfN8ZL1vnBqfM=",
                "gender": 0,
                "is_cancelled": false,
                "profile_gender": 1,
                "user_avatar": "https://p3-novel.byteimg.com/img/novel-static/3abe6a50e39b4bf1ba7c29f33074e1a8~tplv-1yzifmftcy-expand:200:0:0.png",
                "user_id": "78498782522",
                "user_name": "爱吃咖喱小龙虾的涛哥"
              },
              "expand_extra": {},
              "user_id": "78498782522",
              "user_relation": {
                "can_follow": true,
                "relation_type": 1
              },
              "user_tag": {
                "fan_rank_num": 0,
                "fan_ranklist_title": "",
                "is_author": false,
                "is_blue_vip": false,
                "is_cp": false,
                "is_official_cert": false,
                "is_vip": false,
                "user_title_info": []
              }
            }
          },
          "expand": {
            "book_id": "7165309701129767968",
            "book_info": {
              "abstract": "孤儿李星月穿越南宋，本打算拜入全真教，结果被拒。\n成为全真内照顾菜园子的小童儿，心有不甘的他盗了王重阳的墓，得到九阴真经。\n又去少林寻得九阳神功，在小菜园内勤学苦练。\n神功有成后，下山闯荡江湖，成为和赤练仙子齐名的无情仙君。\n并称江湖两大祸害。",
              "audio_thumb_uri": "https://p3-novel.byteimg.com/origin/novel-static/8ae763e02e282c82a0735025ccbc0de9",
              "author": "小米虫",
              "author_id": "",
              "book_id": "7165309701129767968",
              "book_name": "穿越神雕之江湖祸害",
              "book_short_name": "神雕小无赖",
              "book_type": "0",
              "color_dominate": "#e0c8d0",
              "creation_status": "1",
              "genre": "0",
              "genre_type": "0",
              "read_count_text": "7.9万人在读",
              "reader_schema": {
                "authorize_type": "1",
                "category_schema": "[{\"category_id\":1016,\"name\":\"男频衍生\",\"schema\":\"dragon1967://newCategoryDetail?id=1016&name=男频衍生&genre_type=0&gender=1&source=detail\"},{\"category_id\":37,\"name\":\"穿越\",\"schema\":\"dragon1967://newCategoryDetail?id=37&name=穿越&genre_type=0&gender=1&source=detail\"},{\"category_id\":16,\"name\":\"武侠\",\"schema\":\"dragon1967://newCategoryDetail?id=16&name=武侠&genre_type=0&gender=1&source=detail\"},{\"category_id\":384,\"name\":\"无敌\",\"schema\":\"dragon1967://newCategoryDetail?id=384&name=无敌&genre_type=0&gender=1&source=detail\"},{\"category_id\":522,\"name\":\"打脸\",\"schema\":\"dragon1967://newCategoryDetail?id=522&name=打脸&genre_type=0&gender=1&source=detail\"},{\"category_id\":538,\"name\":\"同人\",\"schema\":\"dragon1967://newCategoryDetail?id=538&name=同人&genre_type=0&gender=1&source=detail\"},{\"category_id\":1079,\"name\":\"衍生\",\"schema\":\"dragon1967://newCategoryDetail?id=1079&name=衍生&genre_type=0&gender=1&source=detail\"}]",
                "first_chapter_item_id": "7165314974024532517",
                "read_count": "78219",
                "title_page_tags": "",
                "word_number": "975670"
              },
              "relate_post_id": "",
              "relate_post_schema": "",
              "score": "7.5",
              "serial_count": "366",
              "tags": "男频衍生,武侠,穿越,无敌,打脸,同人,衍生",
              "thumb_url": "https://p3-reading-sign.fqnovelpic.com/novel-pic/77f19d5bced9088f8aecb98b31519b8b~tplv-noop.image?lk3s=9b9bd2b1&x-expires=1779271519&x-signature=xlW9H3PKxpPWz4n4Z0S83%2BH04p0%3D",
              "tomato_book_status": "1"
            },
            "book_info_list": [],
            "common_stat": {},
            "creator_id": "63700036741",
            "extra": {
              "comment_jump_schema": "",
              "novelapp_read_item_cnt": "379"
            },
            "log_extra": {
              "recommend_info": "{\"channel_id\":\"\",\"request_id\":\"20260321180519098A676446F773843AC5\"}"
            },
            "relate_info_list": [],
            "reply_show_count": 0,
            "reply_show_row": 0,
            "score": "10",
            "score_suffix_text": "阅读13小时后点评"
          },
          "stat": {
            "digg_count": 5,
            "forwarded_count": 0,
            "listen_duration": 0,
            "read_book_count": 0,
            "read_duration": 48312,
            "reply_count": 0,
            "show_pv": 1627
          },
          "user_action": {
            "author": 0,
            "is_author_stick": false,
            "stick_position": 0,
            "user_digg": false,
            "user_disagree": false
          }
        },
        "data_type": 4
      }
    ],
    "extra": {
      "book_info": {
        "abstract": "",
        "audio_thumb_uri": "",
        "author": "",
        "author_id": "",
        "book_id": "7165309701129767968",
        "book_name": "",
        "book_type": "",
        "color_dominate": "",
        "creation_status": "",
        "genre": "",
        "genre_type": "",
        "score": "",
        "serial_count": "",
        "tags": "",
        "thumb_url": "",
        "tomato_book_status": ""
      },
      "filter_tag": [],
      "hot_word_search": [],
      "score_cnt": 8621,
      "score_text": "8621人点评"
    }
  },
  "debug_info": "",
  "log_id": "20260321180519098A676446F773843AC5",
  "message": "请求成功"
}