{
  "BaseResp": {
    "StatusCode": 0,
    "StatusMessage": "success"
  },
  "code": 0,
  "data": {
    "common_list_info": {
      "cursor": "{\"session_id\":\"\",\"offset\":400}",
      "has_more": false,
      "total": 7
    },
    "data_list": [
      {
        "comment": {
          "comment_id": "7473049483523932952",
          "common": {
            "comment_type": 0,
            "content": {
              "image_data_list": {},
              "text": "好久没有完整的看我一本书了"
            },
            "content_type": 0,
            "create_timestamp": 1739959782,
            "group_id": "7343834412775132222",
            "service_id": 2,
            "status": 1,
            "user_info": {
              "base_info": {
                "description": "写的是什么乱七八糟的东西",
                "encode_user_id": "#c1967_MTk2NzE5NjcxOTY3MTk2N82qZ9Gx9opz7SQimjTP8w9B57Bw/UUdXlLbhRFYj7m3",
                "gender": 1,
                "is_cancelled": false,
                "profile_gender": 1,
                "user_avatar": "http://p3-reading-sign.fqnovelpic.com/tos-cn-i-1yzifmftcy/8b1a12e812974092aa6246c299e6cebc~tplv-s85hriknmn-jpeg-v1:144:0.jpeg?lk3s=9b9bd2b1&x-expires=1776623603&x-signature=9iMTPFWpmsPAHQJnAElcMdEpAxo%3D",
                "user_id": "2713226250554004",
                "user_name": "侠跻芭泄"
              },
              "expand_extra": {},
              "user_id": "2713226250554004",
              "user_relation": {
                "can_follow": true,
                "relation_type": 1
              },
              "user_tag": {
                "fan_rank_num": 0,
                "fan_ranklist_title": "",
                "is_author": false,
                "is_blue_vip": false,
                "is_cp": false,
                "is_official_cert": false,
                "is_vip": false,
                "sticker": {
                  "expire_time": 1770811253,
                  "is_worn": true,
                  "sticker": {
                    "add_context": "",
                    "bg_color": "#FFE4D8",
                    "can_worn": false,
                    "id": 4,
                    "name": "元气满满",
                    "small_url": "https://p3-novel.byteimg.com/origin/novel-static/9b065c2d8cda96cbf7fdda5c311d871a",
                    "sticker_type": 1,
                    "url": "https://p3-novel.byteimg.com/origin/novel-static/d04cdb6a2447c1029287dc9120659d09"
                  }
                },
                "user_title_info": [
                  {
                    "en_title": "vip",
                    "icon": "{\"icon_default_url\":\"https://p3-novel.byteimg.com/origin/novel-static/0a6117024b55cf7a088043cdb8fa5d48\",\"icon_dark_url\":\"https://p6-novel.byteimg.com/origin/novel-static/9d81e6d86e7f5048ab14f7f77e72ac0f\",\"icon_width\":26,\"icon_height\":16}",
                    "intro": "{\"title_name\":\"vip\",\"title_id\":\"vip\",\"icon_type\":1}",
                    "is_author_title": false,
                    "is_vip_title": true,
                    "zh_title": "vip"
                  }
                ]
              }
            }
          },
          "expand": {
            "book_id": "7343834412775132222",
            "book_info": {
              "abstract": "一朝穿越，成了后宫带把的太监？ \n 从后宫，走向世界，从太监，到万世主宰！ 猥琐发育，别浪！……",
              "audio_thumb_uri": "https://p3-novel.byteimg.com/img/novel-pic/31092b1705347ec075bbca4489fc5cff~tplv-tt-cs0:440:440.image",
              "author": "含笑看海洋",
              "author_id": "",
              "book_id": "7343834412775132222",
              "book_name": "从攻略女帝开始权倾天下",
              "book_short_name": "",
              "book_type": "0",
              "color_dominate": "#302020",
              "creation_status": "0",
              "genre": "0",
              "genre_type": "0",
              "read_count_text": "潜力好书",
              "reader_schema": {
                "authorize_type": "0",
                "category_schema": "[{\"category_id\":273,\"name\":\"历史古代\",\"schema\":\"dragon1967://newCategoryDetail?id=273&name=历史古代&genre_type=0&gender=1&source=detail\"},{\"category_id\":12,\"name\":\"历史\",\"schema\":\"dragon1967://newCategoryDetail?id=12&name=历史&genre_type=0&gender=1&source=detail\"},{\"category_id\":91,\"name\":\"多女主\",\"schema\":\"dragon1967://newCategoryDetail?id=91&name=多女主&genre_type=0&gender=1&source=detail\"},{\"category_id\":378,\"name\":\"女帝\",\"schema\":\"dragon1967://newCategoryDetail?id=378&name=女帝&genre_type=0&gender=1&source=detail\"},{\"category_id\":452,\"name\":\"架空\",\"schema\":\"dragon1967://newCategoryDetail?id=452&name=架空&genre_type=0&gender=1&source=detail\"},{\"category_id\":852,\"name\":\"魂穿\",\"schema\":\"dragon1967://newCategoryDetail?id=852&name=魂穿&genre_type=0&gender=1&source=detail\"}]",
                "first_chapter_item_id": "7412495115626761278",
                "read_count": "318",
                "title_page_tags": "",
                "word_number": "1972422"
              },
              "relate_post_id": "",
              "relate_post_schema": "",
              "score": "0",
              "serial_count": "956",
              "tags": "历史古代,历史,多女主,女帝,架空,魂穿",
              "thumb_url": "https://p3-reading-sign.fqnovelpic.com/novel-pic/31092b1705347ec075bbca4489fc5cff~tplv-noop.image?lk3s=9b9bd2b1&x-expires=1779253438&x-signature=2PUeNAVWlfRPnh4cMVBqXGDBlOk%3D",
              "tomato_book_status": "1"
            },
            "book_info_list": [],
            "common_stat": {},
            "creator_id": "0",
            "extra": {
              "comment_jump_schema": "",
              "novelapp_read_item_cnt": "965"
            },
            "relate_info_list": [],
            "reply_show_count": 1,
            "reply_show_row": 3,
            "score": "10",
            "score_suffix_text": "阅读22小时后点评"
          },
          "stat": {
            "digg_count": 0,
            "forwarded_count": 0,
            "listen_duration": 0,
            "read_book_count": 0,
            "read_duration": 80060,
            "reply_count": 0,
            "show_pv": 1090
          },
          "user_action": {
            "author": 0,
            "is_author_stick": false,
            "stick_position": 0,
            "user_digg": false,
            "user_disagree": false
          }
        },
        "data_type": 4
      },
      {
        "comment": {
          "addition_comment": {
            "comment_id": "7494172678925124377",
            "common": {
              "comment_type": -90,
              "content": {
                "image_data_list": {},
                "text": "然后再说两句！神龙诀这开挂的内功！总是会有人比主角力量大！刚刚把内功增强，又有一个比主角厉害的人出来！好毒！\n看了250多章！兴趣就消失了！我弃书了！等后面的人入坑吧！"
              },
              "content_type": 0,
              "create_timestamp": 1744876846,
              "group_id": "7343834412775132222",
              "service_id": 13,
              "status": 1,
              "user_info": {
                "base_info": {},
                "expand_extra": {},
                "user_id": "1675275502891860"
              }
            },
            "expand": {
              "book_id": "7343834412775132222",
              "book_info_list": [],
              "common_stat": {},
              "creator_id": "0",
              "extra": {
                "comment_jump_schema": "",
                "novelapp_read_item_cnt": "365"
              },
              "relate_info_list": [],
              "reply_show_count": 0,
              "reply_show_row": 0,
              "score": "8",
              "score_suffix_text": "阅读14小时后追评"
            },
            "stat": {
              "digg_count": 0,
              "forwarded_count": 0,
              "listen_duration": 43865,
              "read_book_count": 0,
              "read_duration": 51972,
              "reply_count": 0,
              "show_pv": 0
            },
            "user_action": {
              "author": 0,
              "is_author_stick": false,
              "stick_position": 0,
              "user_digg": false,
              "user_disagree": false
            }
          },
          "comment_id": "7494164062948262681",
          "common": {
            "comment_type": 31,
            "content": {
              "image_data_list": {},
              "text": "看了200多章！八极拳，太极拳！格斗术之类的！都不会！至少得看过一些视频的吧！好歹打两招都不会？有内功，没有战斗技巧？所以不是穿越者？\n可是又会一些现代技术！所以也是穿越者的必备技能！\n就这么故意下毒？"
            },
            "content_type": 0,
            "create_timestamp": 1744876421,
            "group_id": "7343834412775132222",
            "service_id": 2,
            "status": 1,
            "user_info": {
              "base_info": {
                "description": "你所见到的都是我，说我好、坏，我都不会反驳。我就是我！",
                "encode_user_id": "#c1967_MTk2NzE5NjcxOTY3MTk2N/1Ebtuq0PlVNaKPgUm+Q6sPQtpBqAwJVgedtrJEtboI",
                "gender": 1,
                "is_cancelled": false,
                "profile_gender": 1,
                "user_avatar": "http://p3-reading-sign.fqnovelpic.com/tos-cn-i-1yzifmftcy/c8a93377109142edac2af2271cad0aa3~tplv-s85hriknmn-jpeg-v1:144:0.jpeg?lk3s=9b9bd2b1&x-expires=1776618496&x-signature=Jh7P%2FCBw61KbRTDoIHPpi5QBQsA%3D",
                "user_id": "1675275502891860",
                "user_name": "我與嘟毒不共戴天"
              },
              "expand_extra": {},
              "user_id": "1675275502891860",
              "user_relation": {
                "can_follow": true,
                "relation_type": 1
              },
              "user_tag": {
                "fan_rank_num": 0,
                "fan_ranklist_title": "",
                "is_author": false,
                "is_blue_vip": false,
                "is_cp": false,
                "is_official_cert": false,
                "is_vip": true,
                "sticker": {
                  "expire_time": 1780736136,
                  "is_worn": true,
                  "sticker": {
                    "add_context": "",
                    "bg_color": "#E4F5CD",
                    "can_worn": false,
                    "id": 3,
                    "name": "烂尾督察员",
                    "small_url": "https://p6-novel.byteimg.com/origin/novel-static/972e1bec4437ce8e045aaf8e3bbfe1aa",
                    "sticker_type": 1,
                    "url": "https://p6-novel.byteimg.com/origin/novel-static/47aabaca7b644a2b0eb9d35477c6d9df"
                  }
                },
                "user_title_info": [
                  {
                    "en_title": "svip",
                    "icon": "{\"icon_default_url\":\"https://p6-novel.byteimg.com/origin/novel-static/07d37b2c30d271228698f77f4f7f7daf\",\"icon_dark_url\":\"https://p6-novel.byteimg.com/origin/novel-static/d67f15fefbb4470bb54c773eb84e90d8\",\"icon_width\":26,\"icon_height\":16}",
                    "intro": "{\"title_name\":\"svip\",\"title_id\":\"svip\",\"icon_type\":1}",
                    "is_author_title": false,
                    "is_vip_title": true,
                    "zh_title": "svip"
                  }
                ]
              }
            }
          },
          "expand": {
            "book_id": "7343834412775132222",
            "book_info": {
              "abstract": "一朝穿越，成了后宫带把的太监？ \n 从后宫，走向世界，从太监，到万世主宰！ 猥琐发育，别浪！……",
              "audio_thumb_uri": "https://p3-novel.byteimg.com/img/novel-pic/31092b1705347ec075bbca4489fc5cff~tplv-tt-cs0:440:440.image",
              "author": "含笑看海洋",
              "author_id": "",
              "book_id": "7343834412775132222",
              "book_name": "从攻略女帝开始权倾天下",
              "book_short_name": "",
              "book_type": "0",
              "color_dominate": "#302020",
              "creation_status": "0",
              "genre": "0",
              "genre_type": "0",
              "read_count_text": "潜力好书",
              "reader_schema": {
                "authorize_type": "0",
                "category_schema": "[{\"category_id\":273,\"name\":\"历史古代\",\"schema\":\"dragon1967://newCategoryDetail?id=273&name=历史古代&genre_type=0&gender=1&source=detail\"},{\"category_id\":12,\"name\":\"历史\",\"schema\":\"dragon1967://newCategoryDetail?id=12&name=历史&genre_type=0&gender=1&source=detail\"},{\"category_id\":91,\"name\":\"多女主\",\"schema\":\"dragon1967://newCategoryDetail?id=91&name=多女主&genre_type=0&gender=1&source=detail\"},{\"category_id\":378,\"name\":\"女帝\",\"schema\":\"dragon1967://newCategoryDetail?id=378&name=女帝&genre_type=0&gender=1&source=detail\"},{\"category_id\":452,\"name\":\"架空\",\"schema\":\"dragon1967://newCategoryDetail?id=452&name=架空&genre_type=0&gender=1&source=detail\"},{\"category_id\":852,\"name\":\"魂穿\",\"schema\":\"dragon1967://newCategoryDetail?id=852&name=魂穿&genre_type=0&gender=1&source=detail\"}]",
                "first_chapter_item_id": "7412495115626761278",
                "read_count": "318",
                "title_page_tags": "",
                "word_number": "1972422"
              },
              "relate_post_id": "",
              "relate_post_schema": "",
              "score": "0",
              "serial_count": "956",
              "tags": "历史古代,历史,多女主,女帝,架空,魂穿",
              "thumb_url": "https://p3-reading-sign.fqnovelpic.com/novel-pic/31092b1705347ec075bbca4489fc5cff~tplv-noop.image?lk3s=9b9bd2b1&x-expires=1779253438&x-signature=2PUeNAVWlfRPnh4cMVBqXGDBlOk%3D",
              "tomato_book_status": "1"
            },
            "book_info_list": [],
            "common_stat": {},
            "creator_id": "0",
            "extra": {
              "comment_jump_schema": "",
              "novelapp_read_item_cnt": "358"
            },
            "relate_info_list": [],
            "reply_show_count": 1,
            "reply_show_row": 3,
            "score": "8",
            "score_suffix_text": "阅读14小时后点评"
          },
          "stat": {
            "digg_count": 3,
            "forwarded_count": 0,
            "listen_duration": 43379,
            "read_book_count": 0,
            "read_duration": 51439,
            "reply_count": 0,
            "show_pv": 487
          },
          "user_action": {
            "author": 0,
            "is_author_stick": false,
            "stick_position": 0,
            "user_digg": false,
            "user_disagree": false
          }
        },
        "data_type": 4
      },
      {
        "comment": {
          "addition_comment": {
            "comment_id": "7494624765611787032",
            "common": {
              "comment_type": 0,
              "content": {
                "image_data_list": {},
                "text": "好看，超好看"
              },
              "content_type": 0,
              "create_timestamp": 1744981817,
              "group_id": "7343834412775132222",
              "service_id": 13,
              "status": 1,
              "user_info": {
                "base_info": {},
                "expand_extra": {},
                "user_id": "4152230155922599"
              }
            },
            "expand": {
              "book_id": "7343834412775132222",
              "book_info_list": [],
              "common_stat": {},
              "creator_id": "0",
              "extra": {
                "comment_jump_schema": "",
                "novelapp_read_item_cnt": "1544"
              },
              "relate_info_list": [],
              "reply_show_count": 0,
              "reply_show_row": 0,
              "score": "10",
              "score_suffix_text": "阅读162小时后追评"
            },
            "stat": {
              "digg_count": 0,
              "forwarded_count": 0,
              "listen_duration": 290652,
              "read_book_count": 0,
              "read_duration": 581531,
              "reply_count": 0,
              "show_pv": 0
            },
            "user_action": {
              "author": 0,
              "is_author_stick": false,
              "stick_position": 0,
              "user_digg": false,
              "user_disagree": false
            }
          },
          "comment_id": "7494619749870764824",
          "common": {
            "comment_type": 0,
            "content": {
              "image_data_list": {},
              "text": "小说嘛看着高兴开心就好，别整的自己多有知识似的，这不对那不对的"
            },
            "content_type": 0,
            "create_timestamp": 1744981777,
            "group_id": "7343834412775132222",
            "service_id": 2,
            "status": 1,
            "user_info": {
              "base_info": {
                "description": "",
                "encode_user_id": "#c1967_MTk2NzE5NjcxOTY3MTk2N1iuss2twDS4Q0IRs93wYJsDhYYuEFhOvX8nGslolrqk",
                "gender": 1,
                "is_cancelled": false,
                "profile_gender": 1,
                "user_avatar": "http://p3-reading-sign.fqnovelpic.com/tos-cn-i-0000/1437c63bc45b464bb1cc6cd6a7b0d4f1~tplv-s85hriknmn-jpeg-v1:144:0.jpeg?lk3s=9b9bd2b1&x-expires=1776614448&x-signature=77B3F2V9HxLK4vsnQuBSstH5PAo%3D",
                "user_id": "4152230155922599",
                "user_name": "爱吃莲藕蜜饯的叶辰笑"
              },
              "expand_extra": {},
              "user_id": "4152230155922599",
              "user_relation": {
                "can_follow": true,
                "relation_type": 1
              },
              "user_tag": {
                "fan_rank_num": 0,
                "fan_ranklist_title": "",
                "is_author": false,
                "is_blue_vip": false,
                "is_cp": false,
                "is_official_cert": false,
                "is_vip": false,
                "sticker": {
                  "expire_time": 1705020673,
                  "is_worn": true,
                  "sticker": {
                    "add_context": "",
                    "bg_color": "#FFE4D8",
                    "can_worn": false,
                    "id": 4,
                    "name": "元气满满",
                    "small_url": "https://p3-novel.byteimg.com/origin/novel-static/9b065c2d8cda96cbf7fdda5c311d871a",
                    "sticker_type": 1,
                    "url": "https://p3-novel.byteimg.com/origin/novel-static/d04cdb6a2447c1029287dc9120659d09"
                  }
                },
                "user_title_info": []
              }
            }
          },
          "expand": {
            "book_id": "7343834412775132222",
            "book_info": {
              "abstract": "一朝穿越，成了后宫带把的太监？ \n 从后宫，走向世界，从太监，到万世主宰！ 猥琐发育，别浪！……",
              "audio_thumb_uri": "https://p3-novel.byteimg.com/img/novel-pic/31092b1705347ec075bbca4489fc5cff~tplv-tt-cs0:440:440.image",
              "author": "含笑看海洋",
              "author_id": "",
              "book_id": "7343834412775132222",
              "book_name": "从攻略女帝开始权倾天下",
              "book_short_name": "",
              "book_type": "0",
              "color_dominate": "#302020",
              "creation_status": "0",
              "genre": "0",
              "genre_type": "0",
              "read_count_text": "潜力好书",
              "reader_schema": {
                "authorize_type": "0",
                "category_schema": "[{\"category_id\":273,\"name\":\"历史古代\",\"schema\":\"dragon1967://newCategoryDetail?id=273&name=历史古代&genre_type=0&gender=1&source=detail\"},{\"category_id\":12,\"name\":\"历史\",\"schema\":\"dragon1967://newCategoryDetail?id=12&name=历史&genre_type=0&gender=1&source=detail\"},{\"category_id\":91,\"name\":\"多女主\",\"schema\":\"dragon1967://newCategoryDetail?id=91&name=多女主&genre_type=0&gender=1&source=detail\"},{\"category_id\":378,\"name\":\"女帝\",\"schema\":\"dragon1967://newCategoryDetail?id=378&name=女帝&genre_type=0&gender=1&source=detail\"},{\"category_id\":452,\"name\":\"架空\",\"schema\":\"dragon1967://newCategoryDetail?id=452&name=架空&genre_type=0&gender=1&source=detail\"},{\"category_id\":852,\"name\":\"魂穿\",\"schema\":\"dragon1967://newCategoryDetail?id=852&name=魂穿&genre_type=0&gender=1&source=detail\"}]",
                "first_chapter_item_id": "7412495115626761278",
                "read_count": "318",
                "title_page_tags": "",
                "word_number": "1972422"
              },
              "relate_post_id": "",
              "relate_post_schema": "",
              "score": "0",
              "serial_count": "956",
              "tags": "历史古代,历史,多女主,女帝,架空,魂穿",
              "thumb_url": "https://p3-reading-sign.fqnovelpic.com/novel-pic/31092b1705347ec075bbca4489fc5cff~tplv-noop.image?lk3s=9b9bd2b1&x-expires=1779253438&x-signature=2PUeNAVWlfRPnh4cMVBqXGDBlOk%3D",
              "tomato_book_status": "1"
            },
            "book_info_list": [],
            "common_stat": {},
            "creator_id": "0",
            "extra": {
              "comment_jump_schema": "",
              "novelapp_read_item_cnt": "1544"
            },
            "relate_info_list": [],
            "reply_show_count": 1,
            "reply_show_row": 3,
            "score": "10",
            "score_suffix_text": "阅读162小时后点评"
          },
          "stat": {
            "digg_count": 0,
            "forwarded_count": 0,
            "listen_duration": 290652,
            "read_book_count": 0,
            "read_duration": 581531,
            "reply_count": 0,
            "show_pv": 629
          },
          "user_action": {
            "author": 0,
            "is_author_stick": false,
            "stick_position": 0,
            "user_digg": false,
            "user_disagree": false
          }
        },
        "data_type": 4
      },
      {
        "comment": {
          "comment_id": "7508849915287585560",
          "common": {
            "comment_type": 0,
            "content": {
              "image_data_list": {},
              "text": "不错的小说。"
            },
            "content_type": 0,
            "create_timestamp": 1748304103,
            "group_id": "7343834412775132222",
            "service_id": 2,
            "status": 1,
            "user_info": {
              "base_info": {
                "description": "",
                "encode_user_id": "#c1967_MTk2NzE5NjcxOTY3MTk2N+uc/cIUoeBocd5dhdGGqUw=",
                "gender": 1,
                "is_cancelled": false,
                "profile_gender": 0,
                "user_avatar": "http://p3-reading-sign.fqnovelpic.com/tos-cn-i-0000/1437c63bc45b464bb1cc6cd6a7b0d4f1~tplv-s85hriknmn-jpeg-v1:144:0.jpeg?lk3s=9b9bd2b1&x-expires=1776614448&x-signature=77B3F2V9HxLK4vsnQuBSstH5PAo%3D",
                "user_id": "364682430385063",
                "user_name": "喜欢金雀梅的楚天道"
              },
              "expand_extra": {},
              "user_id": "364682430385063",
              "user_relation": {
                "can_follow": true,
                "relation_type": 1
              },
              "user_tag": {
                "fan_rank_num": 0,
                "fan_ranklist_title": "",
                "is_author": false,
                "is_blue_vip": false,
                "is_cp": false,
                "is_official_cert": false,
                "is_vip": false,
                "user_title_info": []
              }
            }
          },
          "expand": {
            "book_id": "7343834412775132222",
            "book_info": {
              "abstract": "一朝穿越，成了后宫带把的太监？ \n 从后宫，走向世界，从太监，到万世主宰！ 猥琐发育，别浪！……",
              "audio_thumb_uri": "https://p3-novel.byteimg.com/img/novel-pic/31092b1705347ec075bbca4489fc5cff~tplv-tt-cs0:440:440.image",
              "author": "含笑看海洋",
              "author_id": "",
              "book_id": "7343834412775132222",
              "book_name": "从攻略女帝开始权倾天下",
              "book_short_name": "",
              "book_type": "0",
              "color_dominate": "#302020",
              "creation_status": "0",
              "genre": "0",
              "genre_type": "0",
              "read_count_text": "潜力好书",
              "reader_schema": {
                "authorize_type": "0",
                "category_schema": "[{\"category_id\":273,\"name\":\"历史古代\",\"schema\":\"dragon1967://newCategoryDetail?id=273&name=历史古代&genre_type=0&gender=1&source=detail\"},{\"category_id\":12,\"name\":\"历史\",\"schema\":\"dragon1967://newCategoryDetail?id=12&name=历史&genre_type=0&gender=1&source=detail\"},{\"category_id\":91,\"name\":\"多女主\",\"schema\":\"dragon1967://newCategoryDetail?id=91&name=多女主&genre_type=0&gender=1&source=detail\"},{\"category_id\":378,\"name\":\"女帝\",\"schema\":\"dragon1967://newCategoryDetail?id=378&name=女帝&genre_type=0&gender=1&source=detail\"},{\"category_id\":452,\"name\":\"架空\",\"schema\":\"dragon1967://newCategoryDetail?id=452&name=架空&genre_type=0&gender=1&source=detail\"},{\"category_id\":852,\"name\":\"魂穿\",\"schema\":\"dragon1967://newCategoryDetail?id=852&name=魂穿&genre_type=0&gender=1&source=detail\"}]",
                "first_chapter_item_id": "7412495115626761278",
                "read_count": "318",
                "title_page_tags": "",
                "word_number": "1972422"
              },
              "relate_post_id": "",
              "relate_post_schema": "",
              "score": "0",
              "serial_count": "956",
              "tags": "历史古代,历史,多女主,女帝,架空,魂穿",
              "thumb_url": "https://p3-reading-sign.fqnovelpic.com/novel-pic/31092b1705347ec075bbca4489fc5cff~tplv-noop.image?lk3s=9b9bd2b1&x-expires=1779253438&x-signature=2PUeNAVWlfRPnh4cMVBqXGDBlOk%3D",
              "tomato_book_status": "1"
            },
            "book_info_list": [],
            "common_stat": {},
            "creator_id": "0",
            "extra": {
              "comment_jump_schema": "",
              "novelapp_read_item_cnt": "14"
            },
            "relate_info_list": [],
            "reply_show_count": 1,
            "reply_show_row": 3,
            "score": "10",
            "score_suffix_text": "阅读1小时后点评"
          },
          "stat": {
            "digg_count": 0,
            "forwarded_count": 0,
            "listen_duration": 0,
            "read_book_count": 0,
            "read_duration": 3674,
            "reply_count": 0,
            "show_pv": 398
          },
          "user_action": {
            "author": 0,
            "is_author_stick": false,
            "stick_position": 0,
            "user_digg": false,
            "user_disagree": false
          }
        },
        "data_type": 4
      },
      {
        "comment": {
          "comment_id": "7483800290443920153",
          "common": {
            "comment_type": 0,
            "content": {
              "image_data_list": {},
              "text": "超好看(♥∀♥)"
            },
            "content_type": 0,
            "create_timestamp": 1742465328,
            "group_id": "7343834412775132222",
            "service_id": 2,
            "status": 1,
            "user_info": {
              "base_info": {
                "description": "",
                "encode_user_id": "#c1967_MTk2NzE5NjcxOTY3MTk2N5iKQ9PFBBqRe2Xv/kxf/JI=",
                "gender": 0,
                "is_cancelled": false,
                "profile_gender": 0,
                "user_avatar": "http://p3-reading-sign.fqnovelpic.com/tos-cn-i-0000/8b91e01a7b0242389b43128fe854e4b7~tplv-s85hriknmn-jpeg-v1:144:0.jpeg?lk3s=9b9bd2b1&x-expires=1776616560&x-signature=%2FYXVdYO%2FVKzIgYSc4FplMZloIxQ%3D",
                "user_id": "92794520770",
                "user_name": "爱吃淡麻糊的李夕君"
              },
              "expand_extra": {},
              "user_id": "92794520770",
              "user_relation": {
                "can_follow": true,
                "relation_type": 1
              },
              "user_tag": {
                "fan_rank_num": 0,
                "fan_ranklist_title": "",
                "is_author": false,
                "is_blue_vip": false,
                "is_cp": false,
                "is_official_cert": false,
                "is_vip": false,
                "user_title_info": []
              }
            }
          },
          "expand": {
            "book_id": "7343834412775132222",
            "book_info": {
              "abstract": "一朝穿越，成了后宫带把的太监？ \n 从后宫，走向世界，从太监，到万世主宰！ 猥琐发育，别浪！……",
              "audio_thumb_uri": "https://p3-novel.byteimg.com/img/novel-pic/31092b1705347ec075bbca4489fc5cff~tplv-tt-cs0:440:440.image",
              "author": "含笑看海洋",
              "author_id": "",
              "book_id": "7343834412775132222",
              "book_name": "从攻略女帝开始权倾天下",
              "book_short_name": "",
              "book_type": "0",
              "color_dominate": "#302020",
              "creation_status": "0",
              "genre": "0",
              "genre_type": "0",
              "read_count_text": "潜力好书",
              "reader_schema": {
                "authorize_type": "0",
                "category_schema": "[{\"category_id\":273,\"name\":\"历史古代\",\"schema\":\"dragon1967://newCategoryDetail?id=273&name=历史古代&genre_type=0&gender=1&source=detail\"},{\"category_id\":12,\"name\":\"历史\",\"schema\":\"dragon1967://newCategoryDetail?id=12&name=历史&genre_type=0&gender=1&source=detail\"},{\"category_id\":91,\"name\":\"多女主\",\"schema\":\"dragon1967://newCategoryDetail?id=91&name=多女主&genre_type=0&gender=1&source=detail\"},{\"category_id\":378,\"name\":\"女帝\",\"schema\":\"dragon1967://newCategoryDetail?id=378&name=女帝&genre_type=0&gender=1&source=detail\"},{\"category_id\":452,\"name\":\"架空\",\"schema\":\"dragon1967://newCategoryDetail?id=452&name=架空&genre_type=0&gender=1&source=detail\"},{\"category_id\":852,\"name\":\"魂穿\",\"schema\":\"dragon1967://newCategoryDetail?id=852&name=魂穿&genre_type=0&gender=1&source=detail\"}]",
                "first_chapter_item_id": "7412495115626761278",
                "read_count": "318",
                "title_page_tags": "",
                "word_number": "1972422"
              },
              "relate_post_id": "",
              "relate_post_schema": "",
              "score": "0",
              "serial_count": "956",
              "tags": "历史古代,历史,多女主,女帝,架空,魂穿",
              "thumb_url": "https://p3-reading-sign.fqnovelpic.com/novel-pic/31092b1705347ec075bbca4489fc5cff~tplv-noop.image?lk3s=9b9bd2b1&x-expires=1779253438&x-signature=2PUeNAVWlfRPnh4cMVBqXGDBlOk%3D",
              "tomato_book_status": "1"
            },
            "book_info_list": [],
            "common_stat": {},
            "creator_id": "0",
            "extra": {
              "comment_jump_schema": "",
              "novelapp_read_item_cnt": "1045"
            },
            "relate_info_list": [],
            "reply_show_count": 1,
            "reply_show_row": 3,
            "score": "10",
            "score_suffix_text": "阅读49小时后点评"
          },
          "stat": {
            "digg_count": 0,
            "forwarded_count": 0,
            "listen_duration": 32224,
            "read_book_count": 0,
            "read_duration": 176245,
            "reply_count": 0,
            "show_pv": 721
          },
          "user_action": {
            "author": 0,
            "is_author_stick": false,
            "stick_position": 0,
            "user_digg": false,
            "user_disagree": false
          }
        },
        "data_type": 4
      }
    ],
    "extra": {
      "book_info": {
        "abstract": "一朝穿越，成了后宫带把的太监？ \n 从后宫，走向世界，从太监，到万世主宰！ 猥琐发育，别浪！……",
        "audio_thumb_uri": "https://p3-novel.byteimg.com/img/novel-pic/31092b1705347ec075bbca4489fc5cff~tplv-tt-cs0:440:440.image",
        "author": "含笑看海洋",
        "author_id": "",
        "book_id": "7343834412775132222",
        "book_name": "从攻略女帝开始权倾天下",
        "book_short_name": "",
        "book_type": "0",
        "color_dominate": "#302020",
        "creation_status": "0",
        "genre": "0",
        "genre_type": "0",
        "read_count_text": "潜力好书",
        "reader_schema": {
          "authorize_type": "0",
          "category_schema": "[{\"category_id\":273,\"name\":\"历史古代\",\"schema\":\"dragon1967://newCategoryDetail?id=273&name=历史古代&genre_type=0&gender=1&source=detail\"},{\"category_id\":12,\"name\":\"历史\",\"schema\":\"dragon1967://newCategoryDetail?id=12&name=历史&genre_type=0&gender=1&source=detail\"},{\"category_id\":91,\"name\":\"多女主\",\"schema\":\"dragon1967://newCategoryDetail?id=91&name=多女主&genre_type=0&gender=1&source=detail\"},{\"category_id\":378,\"name\":\"女帝\",\"schema\":\"dragon1967://newCategoryDetail?id=378&name=女帝&genre_type=0&gender=1&source=detail\"},{\"category_id\":452,\"name\":\"架空\",\"schema\":\"dragon1967://newCategoryDetail?id=452&name=架空&genre_type=0&gender=1&source=detail\"},{\"category_id\":852,\"name\":\"魂穿\",\"schema\":\"dragon1967://newCategoryDetail?id=852&name=魂穿&genre_type=0&gender=1&source=detail\"}]",
          "first_chapter_item_id": "7412495115626761278",
          "read_count": "318",
          "title_page_tags": "",
          "word_number": "1972422"
        },
        "relate_post_id": "",
        "relate_post_schema": "",
        "score": "0",
        "serial_count": "956",
        "tags": "历史古代,历史,多女主,女帝,架空,魂穿",
        "thumb_url": "https://p3-reading-sign.fqnovelpic.com/novel-pic/31092b1705347ec075bbca4489fc5cff~tplv-noop.image?lk3s=9b9bd2b1&x-expires=1779253438&x-signature=2PUeNAVWlfRPnh4cMVBqXGDBlOk%3D",
        "tomato_book_status": "1"
      },
      "ignore_reader_info": {
        "chapter_data_list": [],
        "cur_item_order": 0,
        "serial_count": 0
      },
      "score_cnt": 0
    }
  },
  "debug_info": "",
  "log_id": "20260321130358A40BCE8D632F1F264D7F",
  "message": "请求成功"
}